nonebot_plugin_simdraw/__init__.py
nonebot_plugin_simdraw/data_source.py
nonebot_plugin_simdraw-0.1.4.dist-info/LICENSE
nonebot_plugin_simdraw-0.1.4.dist-info/WHEEL
nonebot_plugin_simdraw-0.1.4.dist-info/METADATA
nonebot_plugin_simdraw-0.1.4.dist-info/RECORD
