Metadata-Version: 2.1
Name: nonebot-plugin-simdraw
Version: 0.1.4
Summary: A phonegame draw simulator plugin for nonebot2
Home-page: https://github.com/abrahum/nonebot_plugin_simdraw
License: GPLv3
Keywords: nonebot,nonebot2,draw
Author: abrahumlink
Author-email: 307887491@qq.com
Requires-Python: >=3.7,<4.0
Classifier: License :: Other/Proprietary License
Classifier: Programming Language :: Python :: 3
Classifier: Programming Language :: Python :: 3.7
Classifier: Programming Language :: Python :: 3.8
Classifier: Programming Language :: Python :: 3.9
Requires-Dist: nonebot2 (>=2.0.0-alpha.8,<3.0.0)
Requires-Dist: ujson (>=4.0.1,<5.0.0)
Project-URL: Documentation, https://github.com/abrahum/nonebot_plugin_simdraw#readme
Project-URL: Repository, https://github.com/abrahum/nonebot_plugin_simdraw
